vcard_bulk_create/__init__.py
vcard_bulk_create/main.py
vcard_from_csv_morris-0.0.3.dist-info/METADATA
vcard_from_csv_morris-0.0.3.dist-info/WHEEL
vcard_from_csv_morris-0.0.3.dist-info/licenses/LICENSE
vcard_from_csv_morris-0.0.3.dist-info/RECORD
