Metadata-Version: 2.1
Name: vcard_from_csv_morris
Version: 0.0.3
Summary: Generates vCards based on a provided DataFrame and dictionary of column mappings. The script includes various functions to preprocess the data, validate the column mappings, clean and format the contact information, add a prefix to first names, and create and write the vCard entries to a file.
Project-URL: Homepage, https://github.com/k-w-lee/vcard_from_csv_morris
Project-URL: Issues, https://github.com/k-w-lee/vcard_from_csv_morris/issues
Author-email: Morris Lee <info.leekahwin@gmail.com>
License-File: LICENSE
Classifier: License :: OSI Approved :: MIT License
Classifier: Operating System :: OS Independent
Classifier: Programming Language :: Python :: 3
Requires-Python: >=3.8
